repopi/__init__.py
repopi/commands/ai_cli.py
repopi/commands/config_cli.py
repopi/commands/git_cli.py
repopi/commands/github_cli.py
repopi/commands/gitlab_cli.py
repopi/commands/team/__init__.py
repopi/commands/team/changelog.py
repopi/commands/team/config.py
repopi/main.py
repopi/utils/__init__.py
repopi/utils/ai_utils.py
repopi/utils/config.py
repopi/utils/config_utils.py
repopi/utils/exceptions.py
repopi/utils/git_utils.py
repopi/utils/github_utils.py
repopi/utils/gitlab_utils.py
repopi/utils/logging.py
repopi-0.1.3.dist-info/LICENSE
repopi-0.1.3.dist-info/METADATA
repopi-0.1.3.dist-info/WHEEL
repopi-0.1.3.dist-info/entry_points.txt
repopi-0.1.3.dist-info/RECORD
