Metadata-Version: 2.3
Name: repopi
Version: 0.1.3
Summary: An all-in-one developer assistant for Git workflows, hosting, and AI automation.
License: MIT
Keywords: git,cli,automation,ai,developer-tools,github,gitlab
Author: S M Asiful Islam Saky
Author-email: saky.aiu22@gmail.com
Maintainer: S M Asiful Islam Saky
Maintainer-email: saky.aiu22@gmail.com
Requires-Python: >=3.9,<4.0
Classifier: Development Status :: 3 - Alpha
Classifier: Environment :: Console
Classifier: Intended Audience :: Developers
Classifier: License :: OSI Approved :: MIT License
Classifier: Operating System :: OS Independent
Classifier: Programming Language :: Python
Classifier: Programming Language :: Python :: 3
Classifier: Programming Language :: Python :: 3.9
Classifier: Programming Language :: Python :: 3.10
Classifier: Programming Language :: Python :: 3.11
Classifier: Programming Language :: Python :: 3.12
Classifier: Programming Language :: Python :: 3.13
Classifier: Topic :: Software Development :: Libraries :: Python Modules
Classifier: Topic :: Software Development :: Version Control :: Git
Classifier: Topic :: Utilities
Classifier: Typing :: Typed
Requires-Dist: GitPython (>=3.1.31,<4.0.0)
Requires-Dist: PyGithub (>=2.0.0,<3.0.0)
Requires-Dist: cachetools (>=4.0,<6.0)
Requires-Dist: cryptography (>=41.0.5,<45)
Requires-Dist: markdown-it-py (>=2.2.0,<3.0.0)
Requires-Dist: openai (>=1.0.0,<2.0.0)
Requires-Dist: packaging (>=20,<25)
Requires-Dist: pydantic (>=2.7.0,<3.0.0)
Requires-Dist: python-gitlab (>=4.0.0,<5.0.0)
Requires-Dist: rich (>=13.3.5,<13.8.0)
Requires-Dist: tomli (>=2.0.1,<3.0.0)
Requires-Dist: tomli-w (>=1.0.0,<2.0.0)
Requires-Dist: typer[all] (>=0.9.0,<0.10.0)
Project-URL: Documentation, https://github.com/saky-semicolon/repopi#readme
Project-URL: Homepage, https://github.com/saky-semicolon/repopi
Project-URL: Repository, https://github.com/saky-semicolon/repopi
